mydborm/__init__.py
mydborm/db.py
mydborm/fields.py
mydborm/migrations.py
mydborm/model.py
mydborm/dialects/__init__.py
mydborm/dialects/mysql.py
mydborm/dialects/yugabyte.py
mydborm-0.1.0.dist-info/licenses/LICENSE
mydborm-0.1.0.dist-info/METADATA
mydborm-0.1.0.dist-info/WHEEL
mydborm-0.1.0.dist-info/entry_points.txt
mydborm-0.1.0.dist-info/top_level.txt
mydborm-0.1.0.dist-info/RECORD
